<ModOps>
  <!-- Description -->
  <ImyaTweaks Title="Adjustments to range of Immigrants Chapel Building" Description="You can Increase or Decrease the Ranges of the Immigrants Chapel Building" />
  
  <!-- FullSatisfactionDistance -->
  <ModOp Type="replace" GUID="1337502795" Path="/Values/PublicService/FullSatisfactionDistance" ModOpID="ChapelNewFullDistance">
    <FullSatisfactionDistance>35</FullSatisfactionDistance>
  </ModOp>
  <ImyaExpose Path="self::FullSatisfactionDistance" ModOpID="ChapelNewFullDistance" ExposeID="Adjust the Chapel FullSatisfactionDistance to your needs" Description="Adjust the FullSatisfactionDistance of the Chapel ( Mod default settings = 35 )" Kind="Slider">
    <SliderDefinition Min="0" Max="50" Stepping="1" />
  </ImyaExpose>
  
  <!-- NoSatisfactionDistance -->
  <ModOp Type="replace" GUID="1337502795" Path="/Values/PublicService/NoSatisfactionDistance" ModOpID="ChapelNewNoSatisfactionDistance">
    <NoSatisfactionDistance>50</NoSatisfactionDistance>
  </ModOp>
  <ImyaExpose Path="self::NoSatisfactionDistance" ModOpID="ChapelNewNoSatisfactionDistance" ExposeID="Adjust the Chapel NoSatisfactionDistance to your needs" Description="Adjust the NoSatisfactionDistance of the Chapel ( Mod default settings = 50 )" Kind="Slider">
    <SliderDefinition Min="0" Max="100" Stepping="1" />
  </ImyaExpose>
</ModOps>